{
  "Workflows": [
    {
      "Path": null,
      "SortBy": 0,
      "VariablesSectionElementsOrder": [],
      "ArgumentsSectionElementsOrder": null,
      "ConstantsSectionElementsOrder": [],
      "AddedNamespaces": null
    },
    {
      "Path": "Main.xaml",
      "SortBy": 0,
      "VariablesSectionElementsOrder": [
        "excelRowCounter&Sequence_1",
        "inputFile&Sequence_1",
        "result&Sequence_2",
        "MathData&Sequence_1"
      ],
      "ArgumentsSectionElementsOrder": [],
      "ConstantsSectionElementsOrder": [],
      "AddedNamespaces": null
    },
    {
      "Path": "ReadInput.xaml",
      "SortBy": 0,
      "VariablesSectionElementsOrder": [
        "selectedFile&Sequence_1"
      ],
      "ArgumentsSectionElementsOrder": [
        "out_SelectedFile",
        "out_MathData"
      ],
      "ConstantsSectionElementsOrder": [],
      "AddedNamespaces": null
    },
    {
      "Path": "Calculation.xaml",
      "SortBy": 0,
      "VariablesSectionElementsOrder": [],
      "ArgumentsSectionElementsOrder": [
        "out_Result",
        "in_Operation",
        "in_num2",
        "in_num1"
      ],
      "ConstantsSectionElementsOrder": [],
      "AddedNamespaces": null
    }
  ]
}